lco/__init__.py
lco-0.1.0.dist-info/WHEEL
lco-0.1.0.dist-info/METADATA
lco-0.1.0.dist-info/RECORD
