Metadata-Version: 2.1
Name: lco
Version: 0.1.0
Summary: A light and global config for research, MVPs and prototype projects.
License: MIT
Author-email: Christoph Minixhofer <christoph.minixhofer@gmail.com>
Requires-Python: >=3.8
Requires-Dist: pyyaml>=6.0
